cddoc/__init__.py
cddoc/cli.py
cddoc/commands/en/exec-auto.md
cddoc/commands/en/exec.md
cddoc/commands/en/plan.md
cddoc/commands/en/socrates.md
cddoc/commands/pt-br/exec-auto.md
cddoc/commands/pt-br/exec.md
cddoc/commands/pt-br/plan.md
cddoc/commands/pt-br/socrates.md
cddoc/config.py
cddoc/handlers/archive_handler.py
cddoc/handlers/progress_handler.py
cddoc/handlers/spec_handler.py
cddoc/init.py
cddoc/new_ticket.py
cddoc/path_resolver.py
cddoc/templates/bug-plan-template.md
cddoc/templates/bug-ticket-template.yaml
cddoc/templates/constitution-template.md
cddoc/templates/en/bug-plan-template.md
cddoc/templates/en/bug-ticket-template.yaml
cddoc/templates/en/constitution-template.md
cddoc/templates/en/enhancement-plan-template.md
cddoc/templates/en/enhancement-ticket-template.yaml
cddoc/templates/en/feature-doc-template.md
cddoc/templates/en/feature-plan-template.md
cddoc/templates/en/feature-ticket-template.yaml
cddoc/templates/en/guide-doc-template.md
cddoc/templates/en/spike-plan-template.md
cddoc/templates/en/spike-ticket-template.yaml
cddoc/templates/enhancement-plan-template.md
cddoc/templates/enhancement-ticket-template.yaml
cddoc/templates/feature-doc-template.md
cddoc/templates/feature-plan-template.md
cddoc/templates/feature-ticket-template.yaml
cddoc/templates/guide-doc-template.md
cddoc/templates/pt-br/bug-plan-template.md
cddoc/templates/pt-br/bug-ticket-template.yaml
cddoc/templates/pt-br/constitution-template.md
cddoc/templates/pt-br/enhancement-plan-template.md
cddoc/templates/pt-br/enhancement-ticket-template.yaml
cddoc/templates/pt-br/feature-doc-template.md
cddoc/templates/pt-br/feature-plan-template.md
cddoc/templates/pt-br/feature-ticket-template.yaml
cddoc/templates/pt-br/guide-doc-template.md
cddoc/templates/pt-br/spike-plan-template.md
cddoc/templates/pt-br/spike-ticket-template.yaml
cddoc/templates/spike-plan-template.md
cddoc/templates/spike-ticket-template.yaml
cddoc/translations/__init__.py
cddoc/translations/en.py
cdd_claude-0.1.5.dist-info/LICENSE
cdd_claude-0.1.5.dist-info/METADATA
cdd_claude-0.1.5.dist-info/WHEEL
cdd_claude-0.1.5.dist-info/entry_points.txt
cdd_claude-0.1.5.dist-info/RECORD
