Metadata-Version: 2.3
Name: cdd-claude
Version: 0.1.5
Summary: AI-first development framework for Claude Code - conversational specs, autonomous planning, context-aware implementation
License: MIT
Keywords: ai,claude,documentation,dev-tools,llm,ai-assisted-development,requirements,specifications
Author: Guilherme Gouw
Author-email: guilherme.gouw@gmail.com
Requires-Python: >=3.9,<4.0
Classifier: Development Status :: 4 - Beta
Classifier: Environment :: Console
Classifier: Framework :: Pytest
Classifier: Intended Audience :: Developers
Classifier: License :: OSI Approved :: MIT License
Classifier: Operating System :: OS Independent
Classifier: Programming Language :: Python :: 3
Classifier: Programming Language :: Python :: 3.9
Classifier: Programming Language :: Python :: 3.10
Classifier: Programming Language :: Python :: 3.11
Classifier: Programming Language :: Python :: 3.12
Classifier: Programming Language :: Python :: 3.13
Classifier: Topic :: Software Development :: Code Generators
Classifier: Topic :: Software Development :: Documentation
Classifier: Topic :: Software Development :: Quality Assurance
Requires-Dist: click (>=8.1.7,<9.0.0)
Requires-Dist: pyyaml (>=6.0.1,<7.0.0)
Requires-Dist: rich (>=13.7.0,<14.0.0)
Project-URL: Homepage, https://github.com/guilhermegouw/context-driven-documentation
Project-URL: Repository, https://github.com/guilhermegouw/context-driven-documentation
